chemtsv2/__init__.py
chemtsv2/abc.py
chemtsv2/cli/__init__.py
chemtsv2/cli/add_cores_to_linker.py
chemtsv2/cli/augment_dataset_with_randomized_smiles.py
chemtsv2/cli/debug_check.py
chemtsv2/cli/result_column_splitter.py
chemtsv2/cli/run.py
chemtsv2/cli/run_mp.py
chemtsv2/cli/train_rnn.py
chemtsv2/mcts.py
chemtsv2/mp_utils.py
chemtsv2/parallel_mcts.py
chemtsv2/preprocessing.py
chemtsv2/scaler.py
chemtsv2/utils.py
chemtsv2-2.0.0.dist-info/LICENSE
chemtsv2-2.0.0.dist-info/METADATA
chemtsv2-2.0.0.dist-info/WHEEL
chemtsv2-2.0.0.dist-info/entry_points.txt
chemtsv2-2.0.0.dist-info/RECORD
