Metadata-Version: 2.1
Name: chemtsv2
Version: 2.0.0
Summary: ChemTSv2 is a flexible and versatile molecule generator based on reinforcement learning with natural language processing.
Home-page: https://github.com/molecule-generator-collection/ChemTSv2
License: MIT
Author: Shoichi Ishida
Author-email: ishida.sho.nm@yokohama-cu.ac.jp
Requires-Python: >=3.11,<3.12
Classifier: Intended Audience :: Science/Research
Classifier: License :: OSI Approved :: MIT License
Classifier: Operating System :: OS Independent
Classifier: Programming Language :: Python :: 3
Classifier: Programming Language :: Python :: 3.11
Provides-Extra: mp
Requires-Dist: joblib
Requires-Dist: mpi4py (>=3.1.5,<3.2.0) ; extra == "mp"
Requires-Dist: numpy (>=1.26.2,<1.27.0)
Requires-Dist: pandas (>=2.1.3,<2.2.0)
Requires-Dist: protobuf (>=4.25.1,<4.26.0)
Requires-Dist: pyyaml
Requires-Dist: rdkit (>=2023.9.1,<2023.10.0)
Requires-Dist: selfies (>=2.1.0,<3.0.0)
Requires-Dist: tensorflow (>=2.14.1,<2.15.0)
Requires-Dist: tensorflow-cpu-aws (>=2.14.1,<2.15.0) ; (platform_machine == "arm64" or platform_machine == "aarch64") and sys_platform == "linux"
Requires-Dist: tensorflow-macos (>=2.14.1,<2.15.0) ; platform_machine == "arm64" and sys_platform == "darwin"
Project-URL: Repository, https://github.com/molecule-generator-collection/ChemTSv2
